deep_log/__init__.py
deep_log/analyzer.py
deep_log/config.py
deep_log/config.yaml
deep_log/engine.py
deep_log/factory.py
deep_log/filter.py
deep_log/handler.py
deep_log/main.py
deep_log/meta_filter.py
deep_log/miner.py
deep_log/parser.py
deep_log/record_writer.py
deep_log/utils.py
deep_log-0.0.15.dist-info/LICENSE
deep_log-0.0.15.dist-info/METADATA
deep_log-0.0.15.dist-info/WHEEL
deep_log-0.0.15.dist-info/entry_points.txt
deep_log-0.0.15.dist-info/top_level.txt
deep_log-0.0.15.dist-info/RECORD
