Metadata-Version: 2.1
Name: deep-log
Version: 0.0.15
Summary: log analysis tool
Home-page: https://github.com/linewx/deep-log
Author: Lu Ganlin
Author-email: linewx1981@gmail.com
License: MIT
Platform: UNKNOWN
Requires-Dist: pyyaml (>=5.3)
Requires-Dist: pandas (>=1.0.5)
Requires-Dist: binaryornot (==0.4.4)
